aliyunsdkcore/__init__.py
aliyunsdkcore/client.py
aliyunsdkcore/compat.py
aliyunsdkcore/request.py
aliyunsdkcore/acs_exception/__init__.py
aliyunsdkcore/acs_exception/error_code.py
aliyunsdkcore/acs_exception/error_msg.py
aliyunsdkcore/acs_exception/error_type.py
aliyunsdkcore/acs_exception/exceptions.py
aliyunsdkcore/auth/__init__.py
aliyunsdkcore/auth/credentials.py
aliyunsdkcore/auth/algorithm/__init__.py
aliyunsdkcore/auth/algorithm/sha_hmac1.py
aliyunsdkcore/auth/algorithm/sha_hmac256.py
aliyunsdkcore/auth/composer/__init__.py
aliyunsdkcore/auth/composer/roa_signature_composer.py
aliyunsdkcore/auth/composer/rpc_signature_composer.py
aliyunsdkcore/auth/signers/__init__.py
aliyunsdkcore/auth/signers/access_key_signer.py
aliyunsdkcore/auth/signers/ecs_ram_role_signer.py
aliyunsdkcore/auth/signers/ram_role_arn_signer.py
aliyunsdkcore/auth/signers/rsa_key_pair_signer.py
aliyunsdkcore/auth/signers/signer.py
aliyunsdkcore/auth/signers/signer_factory.py
aliyunsdkcore/auth/signers/sts_token_signer.py
aliyunsdkcore/auth/utils/__init__.py
aliyunsdkcore/data/endpoints.json
aliyunsdkcore/data/retry_config.json
aliyunsdkcore/data/timeout_config.json
aliyunsdkcore/endpoint/__init__.py
aliyunsdkcore/endpoint/chained_endpoint_resolver.py
aliyunsdkcore/endpoint/default_endpoint_resolver.py
aliyunsdkcore/endpoint/endpoint_resolver_base.py
aliyunsdkcore/endpoint/endpoint_resolver_rules.py
aliyunsdkcore/endpoint/local_config_global_endpoint_resolver.py
aliyunsdkcore/endpoint/local_config_regional_endpoint_resolver.py
aliyunsdkcore/endpoint/location_service_endpoint_resolver.py
aliyunsdkcore/endpoint/resolver_endpoint_request.py
aliyunsdkcore/endpoint/user_customized_endpoint_resolver.py
aliyunsdkcore/endpoint/location/DescribeEndpointsRequest.py
aliyunsdkcore/endpoint/location/__init__.py
aliyunsdkcore/http/__init__.py
aliyunsdkcore/http/format_type.py
aliyunsdkcore/http/http_request.py
aliyunsdkcore/http/http_response.py
aliyunsdkcore/http/method_type.py
aliyun_python_sdk_core-2.13.10.dist-info/METADATA
aliyun_python_sdk_core-2.13.10.dist-info/WHEEL
aliyun_python_sdk_core-2.13.10.dist-info/top_level.txt
aliyun_python_sdk_core-2.13.10.dist-info/RECORD
